jupyterlab_sparksql/__init__.py
jupyterlab_sparksql/_version.py
jupyterlab_sparksql/magics/__init__.py
jupyterlab_sparksql/magics/sparksql.py
jupyterlab_sparksql/magics/widget.py
jupyterlab_sparksql-1.1.0.data/data/share/jupyter/labextensions/jupyterlab-sparksql/package.json
jupyterlab_sparksql-1.1.0.data/data/share/jupyter/labextensions/jupyterlab-sparksql/static/568.241643848d12210f39b0.js
jupyterlab_sparksql-1.1.0.data/data/share/jupyter/labextensions/jupyterlab-sparksql/static/747.7ecba06e06bf4ca5847b.js
jupyterlab_sparksql-1.1.0.data/data/share/jupyter/labextensions/jupyterlab-sparksql/static/remoteEntry.cf84e0c5aa4d370967c0.js
jupyterlab_sparksql-1.1.0.data/data/share/jupyter/labextensions/jupyterlab-sparksql/static/style.js
jupyterlab_sparksql-1.1.0.data/data/share/jupyter/labextensions/jupyterlab-sparksql/static/third-party-licenses.json
jupyterlab_sparksql-1.1.0.data/data/share/jupyter/labextensions/jupyterlab-sparksql/install.json
jupyterlab_sparksql-1.1.0.dist-info/METADATA
jupyterlab_sparksql-1.1.0.dist-info/WHEEL
jupyterlab_sparksql-1.1.0.dist-info/licenses/LICENSE
jupyterlab_sparksql-1.1.0.dist-info/RECORD
