Metadata-Version: 2.1
Name: jupyterlab_sparksql
Version: 1.1.0
Summary: A JupyterLab extension that provides SparkSQL magic commands, a SparkSQL syntax highlighter, and visualization widgets.
Project-URL: Homepage, https://github.com/vule24/jupyterlab-sparksql
Project-URL: Bug Tracker, https://github.com/vule24/jupyterlab-sparksql/issues
Project-URL: Repository, https://github.com/vule24/jupyterlab-sparksql.git
Author-email: Vu Le <ltnv24@gmail.com>
License: BSD 3-Clause License
License-File: LICENSE
Classifier: Framework :: Jupyter
Classifier: Framework :: Jupyter :: JupyterLab
Classifier: Framework :: Jupyter :: JupyterLab :: 3
Classifier: Framework :: Jupyter :: JupyterLab :: Extensions
Classifier: Framework :: Jupyter :: JupyterLab :: Extensions :: Prebuilt
Classifier: License :: OSI Approved :: BSD License
Classifier: Programming Language :: Python
Classifier: Programming Language :: Python :: 3
Classifier: Programming Language :: Python :: 3.7
Classifier: Programming Language :: Python :: 3.8
Classifier: Programming Language :: Python :: 3.9
Classifier: Programming Language :: Python :: 3.10
Classifier: Programming Language :: Python :: 3.11
Requires-Python: >=3.7
Requires-Dist: ipywidgets==7.7.2
Requires-Dist: jupyterlab-widgets==1.1.4
Requires-Dist: pandas
Requires-Dist: plotly
